cocas/__init__.py
cocas/antlr-generate.sh
cocas/assembler/__init__.py
cocas/assembler/assembler.py
cocas/assembler/ast_builder.py
cocas/assembler/ast_nodes.py
cocas/assembler/code_block.py
cocas/assembler/exceptions.py
cocas/assembler/generated/__init__.py
cocas/assembler/generated/AsmLexer.py
cocas/assembler/generated/AsmParser.py
cocas/assembler/generated/AsmParserVisitor.py
cocas/assembler/generated/MacroLexer.py
cocas/assembler/generated/MacroParser.py
cocas/assembler/generated/MacroVisitor.py
cocas/assembler/grammar/AsmLexer.g4
cocas/assembler/grammar/AsmParser.g4
cocas/assembler/grammar/Macro.g4
cocas/assembler/macro_processor.py
cocas/assembler/object_generator.py
cocas/assembler/targets/__init__.py
cocas/assembler/targets/abstract_code_segments.py
cocas/assembler/targets/cdm16/__init__.py
cocas/assembler/targets/cdm16/code_segments.py
cocas/assembler/targets/cdm16/standard.mlb
cocas/assembler/targets/cdm16/target_instructions.py
cocas/assembler/targets/cdm16e/__init__.py
cocas/assembler/targets/cdm16e/standard.mlb
cocas/assembler/targets/cdm16e/target_instructions.py
cocas/assembler/targets/cdm8/__init__.py
cocas/assembler/targets/cdm8/code_segments.py
cocas/assembler/targets/cdm8/standard.mlb
cocas/assembler/targets/cdm8/target_instructions.py
cocas/assembler/targets/cdm8e/__init__.py
cocas/assembler/targets/cdm8e/branches.py
cocas/assembler/targets/cdm8e/code_segments.py
cocas/assembler/targets/cdm8e/instruction_codes.py
cocas/assembler/targets/cdm8e/standard.mlb
cocas/assembler/targets/cdm8e/target_instructions.py
cocas/assembler/targets/target_instructions_protocol.py
cocas/exception_handlers.py
cocas/linker/__init__.py
cocas/linker/debug_export.py
cocas/linker/exceptions.py
cocas/linker/image.py
cocas/linker/linker.py
cocas/linker/targets/__init__.py
cocas/linker/targets/cdm16.json
cocas/linker/targets/cdm16e.json
cocas/linker/targets/cdm8.json
cocas/linker/targets/cdm8e.json
cocas/main.py
cocas/object_file/__init__.py
cocas/object_file/exceptions.py
cdm_devkit-0.2.2.post0.dist-info/entry_points.txt
cdm_devkit-0.2.2.post0.dist-info/METADATA
cdm_devkit-0.2.2.post0.dist-info/WHEEL
cdm_devkit-0.2.2.post0.dist-info/RECORD
