Metadata-Version: 2.1
Name: cdm-devkit
Version: 0.2.2.post0
Summary: Developer tools for CdM processors
Home-page: https://github.com/cdm-processors/cdm-devkit
Author: CdM Processors
Maintainer: Nikolay Repin
Maintainer-email: n.repin@g.nsu.ru
Requires-Python: >=3.10,<4.0
Classifier: Programming Language :: Python :: 3
Classifier: Programming Language :: Python :: 3.10
Classifier: Programming Language :: Python :: 3.11
Classifier: Programming Language :: Python :: 3.12
Classifier: Topic :: Software Development :: Assemblers
Classifier: Topic :: Software Development :: Debuggers
Classifier: Topic :: Software Development :: Disassemblers
Classifier: Topic :: System :: Emulators
Classifier: Topic :: System :: Hardware
Requires-Dist: antlr4-python3-runtime (==4.13.*)
Requires-Dist: bitstruct (>=8.14.1,<9.0.0)
Requires-Dist: colorama (>=0.4.4,<0.5.0)
Requires-Dist: websocket-server (>=0.6.4,<0.7.0)
